pymispgalaxies/__init__.py
pymispgalaxies/api.py
pymispgalaxies/py.typed
pymispgalaxies-1.0.0.dist-info/LICENSE
pymispgalaxies-1.0.0.dist-info/METADATA
pymispgalaxies-1.0.0.dist-info/WHEEL
pymispgalaxies-1.0.0.dist-info/RECORD
