Metadata-Version: 2.1
Name: pymispgalaxies
Version: 1.0.0
Summary: Python API for the MISP Galaxies.
Home-page: https://github.com/MISP/PyMISPGalaxies
License: BSD-3-Clause
Author: Raphaël Vinot
Author-email: raphael.vinot@circl.lu
Requires-Python: >=3.9,<4.0
Classifier: Development Status :: 5 - Production/Stable
Classifier: Environment :: Console
Classifier: Intended Audience :: Science/Research
Classifier: Intended Audience :: Telecommunications Industry
Classifier: License :: OSI Approved :: BSD License
Classifier: Programming Language :: Python
Classifier: Programming Language :: Python :: 3
Classifier: Programming Language :: Python :: 3.9
Classifier: Programming Language :: Python :: 3.10
Classifier: Programming Language :: Python :: 3.11
Classifier: Programming Language :: Python :: 3.12
Classifier: Programming Language :: Python :: 3.13
Classifier: Topic :: Internet
Classifier: Topic :: Security
Requires-Dist: jsonschema (>=4.23.0,<5.0.0)
Project-URL: Repository, https://github.com/MISP/PyMISPGalaxies
